[
  {
    "id": 37,
    "idonline_role_story": 30,
    "name": "达成命运的螺旋<style=red>《救赎》</style>结局",
    "desc": "达成命运的螺旋<style=red>《救赎》</style>结局",
    "behaviour_type": 100701,
    "behaviour_param0": 24,
    "behaviour_param1": 0,
    "behaviour_sparam": "",
    "behaviour_scope": 2,
    "target_value": 1
  },
  {
    "id": 39,
    "idonline_role_story": 32,
    "name": "达成命运的螺旋<style=red>《救赎》</style>结局",
    "desc": "达成命运的螺旋<style=red>《救赎》</style>结局",
    "behaviour_type": 100701,
    "behaviour_param0": 24,
    "behaviour_param1": 0,
    "behaviour_sparam": "",
    "behaviour_scope": 2,
    "target_value": 1
  },
  {
    "id": 40,
    "idonline_role_story": 33,
    "name": "达成命运的螺旋<style=red>《奥古斯特的末路》</style>结局",
    "desc": "达成命运的螺旋<style=red>《奥古斯特的末路》</style>结局",
    "behaviour_type": 100701,
    "behaviour_param0": 22,
    "behaviour_param1": 0,
    "behaviour_sparam": "",
    "behaviour_scope": 2,
    "target_value": 1
  },
  {
    "id": 43,
    "idonline_role_story": 39,
    "name": "通关愚者的旅程第一章<style=red>《一个人的战斗》</style>",
    "desc": "通关愚者的旅程第一章<style=red>《一个人的战斗》</style>",
    "behaviour_type": 200208,
    "behaviour_param0": 218,
    "behaviour_param1": 0,
    "behaviour_sparam": "",
    "behaviour_scope": 2,
    "target_value": 1
  },
  {
    "id": 44,
    "idonline_role_story": 40,
    "name": "通关愚者的旅程第一章<style=red>《一个人的战斗》</style>",
    "desc": "通关愚者的旅程第一章<style=red>《一个人的战斗》</style>",
    "behaviour_type": 200208,
    "behaviour_param0": 218,
    "behaviour_param1": 0,
    "behaviour_sparam": "",
    "behaviour_scope": 2,
    "target_value": 1
  },
  {
    "id": 45,
    "idonline_role_story": 41,
    "name": "通关愚者的旅程第一章<style=red>《一个人的战斗》</style>",
    "desc": "通关愚者的旅程第一章<style=red>《一个人的战斗》</style>",
    "behaviour_type": 200208,
    "behaviour_param0": 218,
    "behaviour_param1": 0,
    "behaviour_sparam": "",
    "behaviour_scope": 2,
    "target_value": 1
  },
  {
    "id": 46,
    "idonline_role_story": 31,
    "name": "通关愚者的旅程第七章<style=red>《骑士之枪》</style>",
    "desc": "通关愚者的旅程第七章<style=red>《骑士之枪》</style>",
    "behaviour_type": 200208,
    "behaviour_param0": 818,
    "behaviour_param1": 0,
    "behaviour_sparam": "",
    "behaviour_scope": 2,
    "target_value": 1
  },
  {
    "id": 47,
    "idonline_role_story": 37,
    "name": "通关命运的螺旋<style=red>《勿言伤痛，这是胜利的代价》</style>章节",
    "desc": "通关命运的螺旋<style=red>《勿言伤痛，这是胜利的代价》</style>章节",
    "behaviour_type": 201002,
    "behaviour_param0": 135,
    "behaviour_param1": 0,
    "behaviour_sparam": "",
    "behaviour_scope": 2,
    "target_value": 1
  },
  {
    "id": 48,
    "idonline_role_story": 38,
    "name": "通关愚者的旅程第三章<style=red>《流浪者之书》</style>",
    "desc": "通关愚者的旅程第三章<style=red>《流浪者之书》</style>",
    "behaviour_type": 200208,
    "behaviour_param0": 417,
    "behaviour_param1": 0,
    "behaviour_sparam": "",
    "behaviour_scope": 2,
    "target_value": 1
  },
  {
    "id": 49,
    "idonline_role_story": 39,
    "name": "通关命运的螺旋<style=red>《铃兰盛开之地》</style>章节",
    "desc": "通关命运的螺旋<style=red>《铃兰盛开之地》</style>章节",
    "behaviour_type": 201002,
    "behaviour_param0": 101,
    "behaviour_param1": 0,
    "behaviour_sparam": "",
    "behaviour_scope": 2,
    "target_value": 1
  },
  {
    "id": 50,
    "idonline_role_story": 40,
    "name": "通关命运的螺旋<style=red>《铃兰盛开之地》</style>章节",
    "desc": "通关命运的螺旋<style=red>《铃兰盛开之地》</style>章节",
    "behaviour_type": 201002,
    "behaviour_param0": 101,
    "behaviour_param1": 0,
    "behaviour_sparam": "",
    "behaviour_scope": 2,
    "target_value": 1
  },
  {
    "id": 51,
    "idonline_role_story": 41,
    "name": "通关命运的螺旋<style=red>《铃兰盛开之地》</style>章节",
    "desc": "通关命运的螺旋<style=red>《铃兰盛开之地》</style>章节",
    "behaviour_type": 201002,
    "behaviour_param0": 101,
    "behaviour_param1": 0,
    "behaviour_sparam": "",
    "behaviour_scope": 2,
    "target_value": 1
  },
  {
    "id": 52,
    "idonline_role_story": 42,
    "name": "通关愚者的旅程第四章<style=red>《意外的集合体》</style>",
    "desc": "通关愚者的旅程第四章<style=red>《意外的集合体》</style>",
    "behaviour_type": 200208,
    "behaviour_param0": 518,
    "behaviour_param1": 0,
    "behaviour_sparam": "",
    "behaviour_scope": 2,
    "target_value": 1
  },
  {
    "id": 54,
    "idonline_role_story": 45,
    "name": "通关命运的螺旋<style=red>《紧紧相连的命运》</style>章节",
    "desc": "通关命运的螺旋<style=red>《紧紧相连的命运》</style>章节",
    "behaviour_type": 201002,
    "behaviour_param0": 134,
    "behaviour_param1": 0,
    "behaviour_sparam": "",
    "behaviour_scope": 2,
    "target_value": 1
  },
  {
    "id": 55,
    "idonline_role_story": 47,
    "name": "通关命运的螺旋<style=red>《勿言伤痛，这是胜利的代价》</style>章节",
    "desc": "通关命运的螺旋<style=red>《勿言伤痛，这是胜利的代价》</style>章节",
    "behaviour_type": 201002,
    "behaviour_param0": 135,
    "behaviour_param1": 0,
    "behaviour_sparam": "",
    "behaviour_scope": 2,
    "target_value": 1
  },
  {
    "id": 57,
    "idonline_role_story": 48,
    "name": "通关命运的螺旋<style=red>《交换》</style>章节",
    "desc": "通关命运的螺旋<style=red>《交换》</style>章节",
    "behaviour_type": 201002,
    "behaviour_param0": 188,
    "behaviour_param1": 0,
    "behaviour_sparam": "",
    "behaviour_scope": 2,
    "target_value": 1
  },
  {
    "id": 58,
    "idonline_role_story": 49,
    "name": "通关命运的螺旋<style=red>《交换》</style>章节",
    "desc": "通关命运的螺旋<style=red>《交换》</style>章节",
    "behaviour_type": 201002,
    "behaviour_param0": 188,
    "behaviour_param1": 0,
    "behaviour_sparam": "",
    "behaviour_scope": 2,
    "target_value": 1
  },
  {
    "id": 62,
    "idonline_role_story": 53,
    "name": "通关命运的螺旋<style=red>《在商言商？》</style>章节",
    "desc": "通关命运的螺旋<style=red>《在商言商？》</style>章节",
    "behaviour_type": 100705,
    "behaviour_param0": 0,
    "behaviour_param1": 0,
    "behaviour_sparam": "35|37|36",
    "behaviour_scope": 1,
    "target_value": 1
  },
  {
    "id": 63,
    "idonline_role_story": 54,
    "name": "通关命运的螺旋<style=red>《在商言商？》</style>章节",
    "desc": "通关命运的螺旋<style=red>《在商言商？》</style>章节",
    "behaviour_type": 100705,
    "behaviour_param0": 0,
    "behaviour_param1": 0,
    "behaviour_sparam": "35|37|36",
    "behaviour_scope": 1,
    "target_value": 1
  }
]